interlinking/__init__.py
interlinking/interlinking.py
interlinking-0.0.4.dist-info/METADATA
interlinking-0.0.4.dist-info/WHEEL
interlinking-0.0.4.dist-info/top_level.txt
interlinking-0.0.4.dist-info/RECORD
