Metadata-Version: 2.1
Name: interlinking
Version: 0.0.4
Summary: Send messages, files or raw data between python codes(servers, computers, ...).
Author: AdioSs (Daniel Karlík)
Author-email: <karlik.dan@gmail.com>
Keywords: python,server,client,data sending,servers communication,sockets
Classifier: Development Status :: 1 - Planning
Classifier: Intended Audience :: Developers
Classifier: Programming Language :: Python :: 3
Classifier: Operating System :: Unix
Classifier: Operating System :: MacOS :: MacOS X
Classifier: Operating System :: Microsoft :: Windows
Requires-Dist: tqdm
